apistar_shell/__init__.py
apistar_shell/commands.py
apistar_shell/compat.py
apistar_shell/components.py
apistar_shell/utils.py
apistar_shell-1.1.dist-info/DESCRIPTION.rst
apistar_shell-1.1.dist-info/METADATA
apistar_shell-1.1.dist-info/RECORD
apistar_shell-1.1.dist-info/WHEEL
apistar_shell-1.1.dist-info/metadata.json
apistar_shell-1.1.dist-info/top_level.txt
